valuta/__init__.py
valuta/base.py
valuta/cli.py
valuta/constants.py
valuta/exceptions.py
valuta/helpers.py
valuta/list_of_circulating_currencies.csv
valuta/registry.py
valuta/scaffolding.py
valuta/shortcuts.py
valuta/utils.py
valuta/contrib/__init__.py
valuta/contrib/django_integration/__init__.py
valuta/contrib/django_integration/context_processors.py
valuta/contrib/django_integration/models.py
valuta/contrib/django_integration/templatetags/__init__.py
valuta/contrib/django_integration/templatetags/valuta_tags.py
valuta/contrib/django_integration/tests/__init__.py
valuta/contrib/django_integration/tests/test_context_processors.py
valuta/contrib/django_integration/tests/test_models.py
valuta/contrib/django_integration/tests/test_templatetags.py
valuta/contrib/sqlalchemy_integration/__init__.py
valuta/contrib/sqlalchemy_integration/types.py
valuta/contrib/sqlalchemy_integration/tests/__init__.py
valuta/contrib/sqlalchemy_integration/tests/test_models.py
valuta/contrib/sqlalchemy_integration/tests/test_types.py
valuta/currencies/__init__.py
valuta/currencies/aed.py
valuta/currencies/afn.py
valuta/currencies/all.py
valuta/currencies/amd.py
valuta/currencies/ang.py
valuta/currencies/aoa.py
valuta/currencies/ars.py
valuta/currencies/aud.py
valuta/currencies/awg.py
valuta/currencies/azn.py
valuta/currencies/bam.py
valuta/currencies/bbd.py
valuta/currencies/bdt.py
valuta/currencies/bgn.py
valuta/currencies/bhd.py
valuta/currencies/bif.py
valuta/currencies/bmd.py
valuta/currencies/bnd.py
valuta/currencies/bob.py
valuta/currencies/brl.py
valuta/currencies/bsd.py
valuta/currencies/btc.py
valuta/currencies/btn.py
valuta/currencies/bwp.py
valuta/currencies/byn.py
valuta/currencies/bzd.py
valuta/currencies/cad.py
valuta/currencies/cdf.py
valuta/currencies/chf.py
valuta/currencies/ckd.py
valuta/currencies/clp.py
valuta/currencies/cny.py
valuta/currencies/cop.py
valuta/currencies/crc.py
valuta/currencies/cup.py
valuta/currencies/cve.py
valuta/currencies/czk.py
valuta-0.3.2.dist-info/LICENSE_GPL2.0.txt
valuta-0.3.2.dist-info/METADATA
valuta-0.3.2.dist-info/WHEEL
valuta-0.3.2.dist-info/entry_points.txt
valuta-0.3.2.dist-info/top_level.txt
valuta-0.3.2.dist-info/RECORD
