Metadata-Version: 2.1
Name: valuta
Version: 0.3.2
Summary: Currencies done right.
Home-page: https://github.com/barseghyanartur/valuta/
Author: Artur Barseghyan
Author-email: artur.barseghyan@gmail.com
License: GPL-2.0-only OR LGPL-2.1-or-later
Project-URL: Bug Tracker, https://github.com/barseghyanartur/valuta/issues
Project-URL: Documentation, https://valuta.readthedocs.io/
Project-URL: Source Code, https://github.com/barseghyanartur/valuta
Project-URL: Changelog, https://valuta.readthedocs.io/en/latest/changelog.html
Keywords: currency
Platform: UNKNOWN
Classifier: Programming Language :: Python :: 3
Classifier: Programming Language :: Python :: 3.6
Classifier: Programming Language :: Python :: 3.7
Classifier: Programming Language :: Python :: 3.8
Classifier: Programming Language :: Python :: 3.9
Classifier: Environment :: Web Environment
Classifier: License :: OSI Approved :: GNU General Public License v2 (GPLv2)
Classifier: License :: OSI Approved :: GNU Lesser General Public License v2 or later (LGPLv2+)
Classifier: Framework :: Django
Classifier: Intended Audience :: Developers
Classifier: Intended Audience :: Financial and Insurance Industry
Classifier: Operating System :: OS Independent
Classifier: Development Status :: 4 - Beta
Requires-Dist: Babel (>=2.1.1)
